odoo9_addon_openeducat_health-9.0.2.4.0-py2.7-nspkg.pth
odoo_addons/openeducat_health/__openerp__.py
odoo_addons/openeducat_health/__init__.py
odoo_addons/openeducat_health/health_menu.xml
odoo_addons/openeducat_health/security/ir.model.access.csv
odoo_addons/openeducat_health/models/health.py
odoo_addons/openeducat_health/models/__init__.py
odoo_addons/openeducat_health/models/student.py
odoo_addons/openeducat_health/models/faculty.py
odoo_addons/openeducat_health/models/health_line.py
odoo_addons/openeducat_health/i18n/openeducat_health.pot
odoo_addons/openeducat_health/views/health_view.xml
odoo_addons/openeducat_health/demo/op.health.line.csv
odoo_addons/openeducat_health/demo/op.health.csv
odoo_addons/openeducat_health/static/description/openeducat_logo.png
odoo_addons/openeducat_health/static/description/openeducat_health_banner.jpg
odoo_addons/openeducat_health/static/description/health.png
odoo_addons/openeducat_health/static/description/index.html
odoo_addons/openeducat_health/static/description/icon.png
odoo9_addon_openeducat_health-9.0.2.4.0.dist-info/top_level.txt
odoo9_addon_openeducat_health-9.0.2.4.0.dist-info/WHEEL
odoo9_addon_openeducat_health-9.0.2.4.0.dist-info/RECORD
odoo9_addon_openeducat_health-9.0.2.4.0.dist-info/metadata.json
odoo9_addon_openeducat_health-9.0.2.4.0.dist-info/DESCRIPTION.rst
odoo9_addon_openeducat_health-9.0.2.4.0.dist-info/METADATA
odoo9_addon_openeducat_health-9.0.2.4.0.dist-info/namespace_packages.txt
